hasherino/__init__.py
hasherino/__main__.py
hasherino/factory.py
hasherino/hasherino_dataclasses.py
hasherino/parse_irc.py
hasherino/pubsub.py
hasherino/storage.py
hasherino/twitch_websocket.py
hasherino/user_auth.py
hasherino/api/chat_history.py
hasherino/api/helix.py
hasherino/api/seven_tv.py
hasherino/components/__init__.py
hasherino/components/account_dialog.py
hasherino/components/chat_container.py
hasherino/components/chat_message.py
hasherino/components/new_message_row.py
hasherino/components/settings_view.py
hasherino/components/status_column.py
hasherino/components/tabs.py
hasherino-0.1.15.dist-info/LICENSE
hasherino-0.1.15.dist-info/METADATA
hasherino-0.1.15.dist-info/WHEEL
hasherino-0.1.15.dist-info/entry_points.txt
hasherino-0.1.15.dist-info/top_level.txt
hasherino-0.1.15.dist-info/RECORD
