Metadata-Version: 2.1
Name: hasherino
Version: 0.1.15
Summary: hasherino is a twitch chat client built using flet
Author-email: Douglas <hashy.software@gmail.com>
Project-URL: Homepage, https://github.com/Hashy-Software/hasherino
Classifier: Programming Language :: Python :: 3
Classifier: License :: OSI Approved :: MIT License
Classifier: Operating System :: OS Independent
Classifier: Development Status :: 2 - Pre-Alpha
Requires-Python: >=3.11
License-File: LICENSE
Requires-Dist: aiohttp ==3.8.5
Requires-Dist: websockets ==11.0.3
Requires-Dist: keyring ==24.2.0
Requires-Dist: flet ==0.19.0
Requires-Dist: certifi ==2023.7.22
Requires-Dist: validators ==0.22.0
Provides-Extra: dev
Requires-Dist: pyinstaller ==6.0.0 ; extra == 'dev'
